pyfactcast/__init__.py
pyfactcast/app/__init__.py
pyfactcast/app/business/__init__.py
pyfactcast/app/business/cli.py
pyfactcast/app/business/entities.py
pyfactcast/app/business/enumerate.py
pyfactcast/app/business/fact.py
pyfactcast/app/business/streams.py
pyfactcast/app/ui/__init__.py
pyfactcast/app/ui/cli.py
pyfactcast/app/ui/enumerate.py
pyfactcast/app/ui/fact.py
pyfactcast/app/ui/streams.py
pyfactcast/client/__init__.py
pyfactcast/client/auth/__init__.py
pyfactcast/client/auth/basic.py
pyfactcast/client/config.py
pyfactcast/client/entities.py
pyfactcast/client/sync.py
pyfactcast/grpc/__init__.py
pyfactcast/grpc/generated/FactStore_pb2.py
pyfactcast/grpc/generated/FactStore_pb2.pyi
pyfactcast/grpc/generated/FactStore_pb2_grpc.py
pyfactcast/grpc/generated/__init__.py
pyfactcast/grpc/proto/FactStore.proto
pyfactcast-0.0.9.dist-info/entry_points.txt
pyfactcast-0.0.9.dist-info/LICENSE
pyfactcast-0.0.9.dist-info/WHEEL
pyfactcast-0.0.9.dist-info/METADATA
pyfactcast-0.0.9.dist-info/RECORD
